spaceone/__init__.py
spaceone/api/__init__.py
spaceone/api/billing/__init__.py
spaceone/api/billing/plugin/__init__.py
spaceone/api/billing/plugin/billing_pb2.py
spaceone/api/billing/plugin/billing_pb2_grpc.py
spaceone/api/billing/plugin/data_source_pb2.py
spaceone/api/billing/plugin/data_source_pb2_grpc.py
spaceone/api/billing/v1/__init__.py
spaceone/api/billing/v1/billing_pb2.py
spaceone/api/billing/v1/billing_pb2_grpc.py
spaceone/api/billing/v1/data_source_pb2.py
spaceone/api/billing/v1/data_source_pb2_grpc.py
spaceone/api/config/__init__.py
spaceone/api/config/v1/__init__.py
spaceone/api/config/v1/domain_config_pb2.py
spaceone/api/config/v1/domain_config_pb2_grpc.py
spaceone/api/config/v1/user_config_pb2.py
spaceone/api/config/v1/user_config_pb2_grpc.py
spaceone/api/core/__init__.py
spaceone/api/core/v1/__init__.py
spaceone/api/core/v1/handler_pb2.py
spaceone/api/core/v1/handler_pb2_grpc.py
spaceone/api/core/v1/query_pb2.py
spaceone/api/core/v1/query_pb2_grpc.py
spaceone/api/core/v1/server_info_pb2.py
spaceone/api/core/v1/server_info_pb2_grpc.py
spaceone/api/cost_analysis/__init__.py
spaceone/api/cost_analysis/plugin/__init__.py
spaceone/api/cost_analysis/plugin/cost_pb2.py
spaceone/api/cost_analysis/plugin/cost_pb2_grpc.py
spaceone/api/cost_analysis/plugin/data_source_pb2.py
spaceone/api/cost_analysis/plugin/data_source_pb2_grpc.py
spaceone/api/cost_analysis/plugin/job_pb2.py
spaceone/api/cost_analysis/plugin/job_pb2_grpc.py
spaceone/api/cost_analysis/v1/__init__.py
spaceone/api/cost_analysis/v1/budget_pb2.py
spaceone/api/cost_analysis/v1/budget_pb2_grpc.py
spaceone/api/cost_analysis/v1/budget_usage_pb2.py
spaceone/api/cost_analysis/v1/budget_usage_pb2_grpc.py
spaceone/api/cost_analysis/v1/cost_pb2.py
spaceone/api/cost_analysis/v1/cost_pb2_grpc.py
spaceone/api/cost_analysis/v1/cost_query_set_pb2.py
spaceone/api/cost_analysis/v1/cost_query_set_pb2_grpc.py
spaceone/api/cost_analysis/v1/custom_widget_pb2.py
spaceone/api/cost_analysis/v1/custom_widget_pb2_grpc.py
cloudforet_api-1.1.1.dist-info/METADATA
cloudforet_api-1.1.1.dist-info/WHEEL
cloudforet_api-1.1.1.dist-info/top_level.txt
cloudforet_api-1.1.1.dist-info/RECORD
