Metadata-Version: 2.1
Name: cloudforet-api
Version: 1.1.1
Summary: SpaceONE API Protobuf
Home-page: https://www.spaceone.dev/
Author: MEGAZONE SpaceONE Team
Author-email: admin@spaceone.dev
License: Apache Software License
Platform: UNKNOWN
